{
  "main": {
    "id": "92a32d6e80c045cd",
    "type": "split",
    "children": [
      {
        "id": "b69e9536697662e1",
        "type": "tabs",
        "children": [
          {
            "id": "c5fdb6bdb624fda9",
            "type": "leaf",
            "state": {
              "type": "image",
              "state": {
                "file": "Pasted Image 20230314225218_248.png"
              }
            }
          }
        ]
      }
    ],
    "direction": "vertical"
  },
  "left": {
    "id": "253208396acebad8",
    "type": "split",
    "children": [
      {
        "id": "dd184af88e76fd91",
        "type": "tabs",
        "children": [
          {
            "id": "e669609d4be51441",
            "type": "leaf",
            "state": {
              "type": "file-explorer",
              "state": {
                "sortOrder": "alphabetical"
              }
            }
          },
          {
            "id": "9ad596ee6e0caa71",
            "type": "leaf",
            "state": {
              "type": "search",
              "state": {
                "query": "",
                "matchingCase": true,
                "explainSearch": false,
                "collapseAll": true,
                "extraContext": false,
                "sortOrder": "alphabetical"
              }
            }
          },
          {
            "id": "329708f313f37f07",
            "type": "leaf",
            "state": {
              "type": "starred",
              "state": {}
            }
          },
          {
            "id": "039ca86cb10e4281",
            "type": "leaf",
            "state": {
              "type": "bookmarks",
              "state": {}
            }
          }
        ]
      }
    ],
    "direction": "horizontal",
    "width": 300
  },
  "right": {
    "id": "2b4095518a73da1c",
    "type": "split",
    "children": [
      {
        "id": "d717ffbbe4b82025",
        "type": "tabs",
        "children": [
          {
            "id": "b5fa019bf5170955",
            "type": "leaf",
            "state": {
              "type": "backlink",
              "state": {
                "file": "Pasted Image 20230314225218_248.png",
                "collapseAll": true,
                "extraContext": true,
                "sortOrder": "alphabetical",
                "showSearch": true,
                "searchQuery": "",
                "backlinkCollapsed": false,
                "unlinkedCollapsed": true
              }
            }
          },
          {
            "id": "edc493e38cb341a8",
            "type": "leaf",
            "state": {
              "type": "outgoing-link",
              "state": {
                "file": "Pasted Image 20230314225218_248.png",
                "linksCollapsed": false,
                "unlinkedCollapsed": true
              }
            }
          },
          {
            "id": "5450f7af7bc5d80b",
            "type": "leaf",
            "state": {
              "type": "tag",
              "state": {
                "sortOrder": "frequency",
                "useHierarchy": true
              }
            }
          },
          {
            "id": "1bd1274e3acafc71",
            "type": "leaf",
            "state": {
              "type": "outline",
              "state": {
                "file": "Pasted Image 20230314225218_248.png"
              }
            }
          },
          {
            "id": "9850ed439c0397c2",
            "type": "leaf",
            "state": {
              "type": "git-view",
              "state": {}
            }
          },
          {
            "id": "86a8baf5dc44e25b",
            "type": "leaf",
            "state": {
              "type": "advanced-tables-toolbar",
              "state": {}
            }
          }
        ],
        "currentTab": 4
      }
    ],
    "direction": "horizontal",
    "width": 454.5
  },
  "left-ribbon": {
    "hiddenItems": {
      "remotely-save:Remotely Save": false,
      "canvas:新建白板": false,
      "switcher:打开快速切换": false,
      "graph:查看关系图谱": false,
      "daily-notes:打开/创建今天的日记": false,
      "templates:插入模板": false,
      "command-palette:打开命令面板": false,
      "table-editor-obsidian:Advanced Tables Toolbar": false,
      "obsidian-excalidraw-plugin:新建 Excalidraw 绘图": false
    }
  },
  "active": "c5fdb6bdb624fda9",
  "lastOpenFiles": [
    "Pasted Image 20230314225233_257.png",
    "nosql/Redis.md",
    "容器/docker基础.md",
    "测试相关/app测试与web测试.md",
    "测试相关/测试的相关流程.md",
    "测试相关/测试常用方法.md",
    "面试/面试.md",
    "自动化/Css选择器.md",
    "容器/docker高级.md",
    "性能/Jmeter.md",
    "性能/性能测试指标（多快好省）.md",
    "性能/性能指标.md",
    "sql/mysql基础.md",
    "linux/命令.md",
    "Pasted Image 20230314230028_262.png",
    "Pasted Image 20230314225218_248.png",
    "面试",
    "自动化/其他选择器.md",
    "自动化/Selenium.md",
    "nosql/mongodb.md",
    "自动化/XPATH.md",
    "sql/锁表.md",
    "sql/查表空间和创建用户.md",
    "sql/查分区.md",
    "python/双链/抽象类.md",
    "金融风险.blinkmind",
    "1.blinkmind",
    "Java/5. 常用方法.md",
    "Java/《Java从入门到精通(JDK17版)》_尚硅谷电子书.pdf",
    "Java/idea快捷键.md",
    "python/双链/匿名函数lamda.md",
    "sql/存储过程调试开启.md",
    "Pasted Image 20230314230611_262.png",
    "Pasted Image 20230314230408_265.png",
    "Pasted Image 20230314230144_252.png",
    "Pasted Image 20230314230043_272.png",
    "Pasted Image 20230314225318_264.png",
    "Excalidraw",
    "实战",
    "Java/spring/Spring Boot笔记急速.pdf",
    "Java/spring/spring ioc.png",
    "Users/southwind/Library",
    "Users/southwind",
    "Users",
    "Pasted image 20230223143534.png"
  ]
}